IRA_vision/__init__.py
IRA_vision/camera.py
IRA_vision/classifier.py
IRA_vision/export.py
IRA_vision/hubconf.py
IRA_vision/label.py
IRA_vision/objectdetection.py
IRA_vision/posecalculator.py
IRA_vision/models/__init__.py
IRA_vision/models/common.py
IRA_vision/models/experimental.py
IRA_vision/models/tf.py
IRA_vision/models/yolo.py
IRA_vision/utils/__init__.py
IRA_vision/utils/activations.py
IRA_vision/utils/augmentations.py
IRA_vision/utils/autoanchor.py
IRA_vision/utils/autobatch.py
IRA_vision/utils/callbacks.py
IRA_vision/utils/dataloaders.py
IRA_vision/utils/downloads.py
IRA_vision/utils/general.py
IRA_vision/utils/loss.py
IRA_vision/utils/metrics.py
IRA_vision/utils/plots.py
IRA_vision/utils/torch_utils.py
IRA_vision/utils/triton.py
IRA_vision/utils/aws/__init__.py
IRA_vision/utils/aws/resume.py
IRA_vision/utils/flask_rest_api/example_request.py
IRA_vision/utils/flask_rest_api/restapi.py
IRA_vision/utils/loggers/__init__.py
IRA_vision/utils/loggers/clearml/__init__.py
IRA_vision/utils/loggers/clearml/clearml_utils.py
IRA_vision/utils/loggers/clearml/hpo.py
IRA_vision/utils/loggers/comet/__init__.py
IRA_vision/utils/loggers/comet/comet_utils.py
IRA_vision/utils/loggers/comet/hpo.py
IRA_vision/utils/loggers/wandb/__init__.py
IRA_vision/utils/loggers/wandb/log_dataset.py
IRA_vision/utils/loggers/wandb/sweep.py
IRA_vision/utils/loggers/wandb/wandb_utils.py
IRA_vision/utils/segment/__init__.py
IRA_vision/utils/segment/augmentations.py
IRA_vision/utils/segment/dataloaders.py
IRA_vision/utils/segment/general.py
IRA_vision/utils/segment/loss.py
IRA_vision/utils/segment/metrics.py
IRA_vision/utils/segment/plots.py
IRA_vision-0.0.1.dist-info/LICENSE
IRA_vision-0.0.1.dist-info/METADATA
IRA_vision-0.0.1.dist-info/WHEEL
IRA_vision-0.0.1.dist-info/top_level.txt
IRA_vision-0.0.1.dist-info/RECORD
